magyc/__init__.py
magyc/benchmark_methods/__init__.py
magyc/benchmark_methods/ellipsoidfit.py
magyc/benchmark_methods/magfactor.py
magyc/benchmark_methods/sar.py
magyc/benchmark_methods/spherefit.py
magyc/benchmark_methods/twostep.py
magyc/methods/__init__.py
magyc/methods/magyc.py
magyc/plots/__init__.py
magyc/plots/plots.py
magyc/sim_data/__init__.py
magyc/sim_data/generate_data.py
magyc/utils/__init__.py
magyc/utils/utils.py
magyc-1.0.0.dist-info/LICENSE.txt
magyc-1.0.0.dist-info/METADATA
magyc-1.0.0.dist-info/WHEEL
magyc-1.0.0.dist-info/RECORD
