Metadata-Version: 2.1
Name: magyc
Version: 1.0.0
Summary: CoMPAS Lab Magnetometer and Gyroscope Calibration (MAGYC)
License: MIT
Author: srodriguez_mbari
Author-email: srodriguez@mbari.org
Requires-Python: >=3.8,<4.0
Classifier: License :: OSI Approved :: MIT License
Classifier: Programming Language :: Python :: 3
Classifier: Programming Language :: Python :: 3.8
Classifier: Programming Language :: Python :: 3.9
Classifier: Programming Language :: Python :: 3.10
Classifier: Programming Language :: Python :: 3.11
Requires-Dist: gtsam (>=4.2,<5.0)
Requires-Dist: jax (>=0.4.1,<0.4.14) ; python_version >= "3.8" and python_version < "3.9"
Requires-Dist: jax (>=0.4.14,<0.4.31) ; python_version >= "3.9" and python_version < "3.10"
Requires-Dist: jax (>=0.4.31,<0.5.0) ; python_version >= "3.10"
Requires-Dist: jaxlib (>=0.4.1,<0.4.14) ; python_version >= "3.8" and python_version < "3.9"
Requires-Dist: jaxlib (>=0.4.14,<0.4.31) ; python_version >= "3.9" and python_version < "3.10"
Requires-Dist: jaxlib (>=0.4.31,<0.5.0) ; python_version >= "3.10"
Requires-Dist: matplotlib (>=3.6.0,<3.8.0) ; python_version >= "3.8" and python_version < "3.9"
Requires-Dist: matplotlib (>=3.8.0,<4.0.0) ; python_version >= "3.9"
Requires-Dist: navlib (>=0.1.5,<0.2.0)
Requires-Dist: numpy (>=1.22,<1.25) ; python_version >= "3.8" and python_version < "3.9"
Requires-Dist: numpy (>=1.25,<2.0) ; python_version >= "3.9"
Requires-Dist: scipy (==1.10.*) ; python_version >= "3.8" and python_version < "3.9"
Requires-Dist: scipy (>=1.11,<1.14) ; python_version >= "3.9" and python_version < "3.10"
Requires-Dist: scipy (>=1.14,<2.0) ; python_version >= "3.10"
